sparql_grammar_pydantic/__init__.py
sparql_grammar_pydantic/grammar.py
sparql_grammar_pydantic/indentation.py
sparql_grammar_pydantic-0.1.11.dist-info/LICENSE
sparql_grammar_pydantic-0.1.11.dist-info/METADATA
sparql_grammar_pydantic-0.1.11.dist-info/WHEEL
sparql_grammar_pydantic-0.1.11.dist-info/RECORD
